LICENSE.txt
MANIFEST.in
README.md
setup.py
estore/server/__init__.py
estore/server/__main__.py
estore/server/app.py
estore/server/builtins.py
estore/server/cli.py
estore/server/db.py
estore/server/errors.py
estore/server/query.py
estore/server/sql.py
estore/server/store.py
estore/server/view.py
estore/server/web.py
estore_server.egg-info/PKG-INFO
estore_server.egg-info/SOURCES.txt
estore_server.egg-info/dependency_links.txt
estore_server.egg-info/entry_points.txt
estore_server.egg-info/requires.txt
estore_server.egg-info/top_level.txt